simple_cmd/__init__.py
simple_cmd/commands.py
simple_cmd/decorators.py
tests/__init__.py
tests/example.py
tests/test_example.py
tests/test_unit.py
simple_cmd-2.0.1.dist-info/LICENSE
simple_cmd-2.0.1.dist-info/METADATA
simple_cmd-2.0.1.dist-info/WHEEL
simple_cmd-2.0.1.dist-info/top_level.txt
simple_cmd-2.0.1.dist-info/RECORD
