Metadata-Version: 2.1
Name: simple-cmd
Version: 2.0.1
Summary: Simple CLI command function definition
Home-page: https://bitbucket.org/coleopter/simple-cmd
Author: Daniel Farré Manzorro
Author-email: d.farre.m@gmail.com
License: UNKNOWN
Platform: UNKNOWN
Classifier: Programming Language :: Python :: 3
Classifier: Programming Language :: Python :: 3.6
Classifier: Programming Language :: Python :: 3.7
Classifier: License :: OSI Approved :: MIT License
Classifier: Operating System :: OS Independent
Classifier: Intended Audience :: Developers
Provides-Extra: dev
Requires-Dist: ipdb ; extra == 'dev'
Requires-Dist: ipython ; extra == 'dev'
Provides-Extra: test
Requires-Dist: pytest-cov ; extra == 'test'
